Pparity/__init__.py
Pparity/main.py
pparity-0.1.0.dist-info/LICENSE
pparity-0.1.0.dist-info/METADATA
pparity-0.1.0.dist-info/WHEEL
pparity-0.1.0.dist-info/RECORD
